{
    "ApplicationConfiguration": {
        "Paths": {
            "Chain": "Chain_{0}",
            "ApplicationLogs": "ApplicationLogs_{0}"
        },
        "P2P": {
            "Port": 20336,
            "WsPort": 10336
        },
        "RPC": {
            "Port": 30336,
            "SslCert": "",
            "SslCertPassword": ""
        },
        "UnlockWallet": {
            "Path": "",
            "Password": "",
            "StartConsensus": false,
            "IsActive": false
        }
    }
}
